src/http_server.py
src/main.py
src/stdio_server.py
src/version.py
src/mcp_servers/__init__.py
src/mcp_servers/xpages_mcp.py
x_pages_mcp-0.1.4.dist-info/METADATA
x_pages_mcp-0.1.4.dist-info/WHEEL
x_pages_mcp-0.1.4.dist-info/entry_points.txt
x_pages_mcp-0.1.4.dist-info/licenses/LICENSE
x_pages_mcp-0.1.4.dist-info/RECORD
