Metadata-Version: 2.4
Name: x-pages-mcp
Version: 0.1.4
Summary: MCP server for X-Pages HTML deployment service
Project-URL: Homepage, https://github.com/xingshulin/x-pages-mcp
Project-URL: Documentation, https://github.com/xingshulin/x-pages-mcp/blob/main/README.md
Project-URL: Repository, https://github.com/xingshulin/x-pages-mcp
Project-URL: Bug Tracker, https://github.com/xingshulin/x-pages-mcp/issues
Author: X-Pages Team
License: MIT License
License-File: LICENSE
Keywords: ai,claude,deployment,html,mcp,model-context-protocol
Classifier: Development Status :: 4 - Beta
Classifier: Framework :: AsyncIO
Classifier: Intended Audience :: Developers
Classifier: License :: OSI Approved :: MIT License
Classifier: Programming Language :: Python :: 3
Classifier: Programming Language :: Python :: 3.10
Classifier: Programming Language :: Python :: 3.11
Classifier: Programming Language :: Python :: 3.12
Classifier: Topic :: Internet :: WWW/HTTP :: HTTP Servers
Classifier: Topic :: Software Development :: Libraries :: Python Modules
Requires-Python: >=3.10
Requires-Dist: fastapi<1.0.0,>=0.100.0
Requires-Dist: fastmcp<3.0.0,>=2.11.3
Requires-Dist: httpcore[socks]<2.0.0,>=1.0.0
Requires-Dist: httpx[socks]<1.0.0,>=0.27.0
Requires-Dist: markdown<4.0.0,>=3.4.0
Requires-Dist: mcp[cli]<2.0.0,>=1.0.0
Requires-Dist: pydantic-settings<3.0.0,>=2.0.0
Requires-Dist: pydantic<3.0.0,>=2.0.0
Requires-Dist: python-dotenv<2.0.0,>=1.0.0
Requires-Dist: uvicorn<1.0.0,>=0.20.0
Provides-Extra: dev
Requires-Dist: mypy; extra == 'dev'
Requires-Dist: pytest; extra == 'dev'
Requires-Dist: pytest-asyncio; extra == 'dev'
Requires-Dist: ruff; extra == 'dev'
